package KotlinåŸºç¡€.pkg7_ä¼´ç”Ÿå¯¹è±¡

class HiKotlin4 {

  companion object MyObject {
    var a: Int = 100

    // ğŸ“¢æ³¨æ„
    // ï¼ˆ2ï¼‰åœ¨JVMä¸Šï¼Œå¯ä»¥å°†ä¼´ç”Ÿå¯¹è±¡çš„æˆå‘˜çœŸæ­£ç”Ÿæˆä¸ºç±»çš„é™æ€æ–¹æ³•ä¸é™æ€å±æ€§ï¼Œæ˜¯é€šè¿‡@JvmStaticæ³¨è§£æ¥å®ç°çš„ã€‚
    // ï¼ˆ3ï¼‰ä¼´ç”Ÿå¯¹è±¡åœ¨ç¼–è¯‘åä¼šç”Ÿæˆä¸€ä¸ªé™æ€å†…éƒ¨ç±»
    @JvmStatic
    fun method() {
      println("method invoked")
    }
  }
}

fun main() {
  HiKotlin4.method()
}

/*
(1) javap åç¼–è¯‘
public final class Kotlinå­¦ä¹ .kotlinåŸºç¡€.pkg7_ä¼´ç”Ÿå¯¹è±¡.HiKotlin4 {
  public static final Kotlinå­¦ä¹ .kotlinåŸºç¡€.pkg7_ä¼´ç”Ÿå¯¹è±¡.HiKotlin4$MyObject MyObject;
  public Kotlinå­¦ä¹ .kotlinåŸºç¡€.pkg7_ä¼´ç”Ÿå¯¹è±¡.HiKotlin4();
  // å‡ºç°åœ¨HiKotlin4ç±»ä¸­ï¼ŒçœŸæ­£æˆä¸ºäº†ç±»çš„é™æ€æ–¹æ³•äº†ã€‚è¿™å°±æ˜¯@JvmStaticæ³¨è§£çš„ä½œç”¨
  public static final void method();
  public static final int access$getA$cp();
  public static final void access$setA$cp(int);
  static {};
}


(2) javap -c å°†å­—èŠ‚ç åç¼–è¯‘å‡ºæ¥
public final class Kotlinå­¦ä¹ .kotlinåŸºç¡€.pkg7_ä¼´ç”Ÿå¯¹è±¡.HiKotlin4 {
  public static final Kotlinå­¦ä¹ .kotlinåŸºç¡€.pkg7_ä¼´ç”Ÿå¯¹è±¡.HiKotlin4$MyObject MyObject;

  public Kotlinå­¦ä¹ .kotlinåŸºç¡€.pkg7_ä¼´ç”Ÿå¯¹è±¡.HiKotlin4();
    Code:
       0: aload_0
       1: invokespecial #8                  // Method java/lang/Object."<init>":()V
       4: return

  public static final void method();
    Code:
       0: getstatic     #16                 // Field MyObject:LKotlinå­¦ä¹ /kotlinåŸºç¡€.pkg7_ä¼´ç”Ÿå¯¹è±¡/HiKotlin4$MyObject;
       3: invokevirtual #20                 // Method Kotlinå­¦ä¹ /kotlinåŸºç¡€.pkg7_ä¼´ç”Ÿå¯¹è±¡/HiKotlin4$MyObject.method:()V
       6: return

  public static final int access$getA$cp();
    Code:
       0: getstatic     #26                 // Field a:I
       3: ireturn

  public static final void access$setA$cp(int);
    Code:
       0: iload_0
       1: putstatic     #26                 // Field a:I
       4: return

  static {};
    Code:
       0: new           #18                 // class Kotlinå­¦ä¹ /kotlinåŸºç¡€.pkg7_ä¼´ç”Ÿå¯¹è±¡/HiKotlin4$MyObject
       3: dup
       4: aconst_null
       5: invokespecial #33                 // Method Kotlinå­¦ä¹ /kotlinåŸºç¡€.pkg7_ä¼´ç”Ÿå¯¹è±¡/HiKotlin4$MyObject."<init>":(Lkotlin/jvm/internal/DefaultConstructorMarker;)V
       8: putstatic     #16                 // Field MyObject:LKotlinå­¦ä¹ /kotlinåŸºç¡€.pkg7_ä¼´ç”Ÿå¯¹è±¡/HiKotlin4$MyObject;
      11: bipush        100
      13: putstatic     #26                 // Field a:I
      16: return
}


 */
