package KotlinåŸºç¡€.pkg7_ä¼´ç”Ÿå¯¹è±¡

class HiKotlin3 {

  companion object MyObject {

    var a: Int = 100

    fun method() {
      println("method invoked")
    }
  }
}

fun main() {

  val v = HiKotlin3.MyObject
  println(v.javaClass) // è¾“å‡º class KotlinåŸºç¡€.pkg7_ä¼´ç”Ÿå¯¹è±¡.HiKotlin3$MyObject
  // MyObjectç±»å‹æ˜¯KotlinåŸºç¡€.pkg7_ä¼´ç”Ÿå¯¹è±¡.HiKotlin3$MyObjectï¼Œclassåå­—å«ä½œMyObjectï¼Œè€Œä¸”è¿˜æ˜¯HiKotlin3çš„ä¸€ä¸ªå†…éƒ¨ç±»ã€‚

  // .javaClass - Returns the runtime Java class of this object.ï¼ˆè¿”å›è¿™ä¸ªå¯¹è±¡åœ¨è¿è¡ŒæœŸæ‰€å¯¹åº”çš„Javaç±»å‹ï¼‰

  // ğŸ“¢æ³¨æ„
  // ï¼ˆ1ï¼‰è™½ç„¶ä¼´ç”Ÿå¯¹è±¡çš„æˆå‘˜çœ‹èµ·æ¥åƒæ˜¯Javaä¸­çš„é™æ€æˆå‘˜ï¼Œä½†åœ¨è¿è¡ŒæœŸï¼Œä»–ä»¬ä¾æ—§æ˜¯çœŸå®å¯¹è±¡çš„å®ä¾‹æˆå‘˜
  // å…·ä½“çœ‹: methodæ–¹æ³•ä»ä½¿ç”¨è§’åº¦çœ‹ï¼Œå°±å¥½åƒæ˜¯HiKotlin3ç±»ä¸­çš„ä¸€ä¸ªé™æ€æ–¹æ³•ã€‚ä½†å…¶å®å¹¶ä¸æ˜¯é™æ€æ–¹æ³•ã€‚

}

/*
(1) javap åç¼–è¯‘ï¼šè¿›å…¥åˆ° "Kotlinå­¦ä¹ /Kotlinå­¦ä¹ /"ç›®å½•ï¼Œ"javap kotlinåŸºç¡€.pkg7_ä¼´ç”Ÿå¯¹è±¡.HiKotlin3"
public final class Kotlinå­¦ä¹ .kotlinåŸºç¡€.pkg7_ä¼´ç”Ÿå¯¹è±¡.HiKotlin3 {
  // éªŒè¯: (1)è™½ç„¶ä¼´ç”Ÿå¯¹è±¡çš„æˆå‘˜çœ‹èµ·æ¥åƒæ˜¯Javaä¸­çš„é™æ€æˆå‘˜ï¼Œä½†åœ¨è¿è¡ŒæœŸï¼Œä»–ä»¬ä¾æ—§æ˜¯çœŸå®å¯¹è±¡çš„å®ä¾‹æˆå‘˜
  // method()æ–¹æ³•å¹¶æ²¡æœ‰å‡ºç°ï¼ŒHiKotlin3.method()ï¼Œä¸­é—´è¿˜æ˜¯é€šè¿‡MyObjectåšäº†ä¸€å±‚è½¬æ¢ï¼Œæœ€ç»ˆè½¬æ¢æˆï¼ŒHiKotlin3è®¿é—®å®ƒé‡Œé¢çš„MyObjectï¼Œé€šè¿‡å¯¹è±¡è°ƒç”¨method()æ–¹æ³•ã€‚
  // è¿™å°±æ˜¯å®šä¹‰çš„companion objectï¼Œç±»å‹æ˜¯Kotlinå­¦ä¹ .kotlinåŸºç¡€.pkg7_ä¼´ç”Ÿå¯¹è±¡.HiKotlin3$MyObject(é™æ€å†…éƒ¨ç±»çš„ç±»å‹)ï¼Œä¸”æ˜¯é™æ€çš„static
  public static final Kotlinå­¦ä¹ .kotlinåŸºç¡€.pkg7_ä¼´ç”Ÿå¯¹è±¡.HiKotlin3$MyObject MyObject;
  public Kotlinå­¦ä¹ .kotlinåŸºç¡€.pkg7_ä¼´ç”Ÿå¯¹è±¡.HiKotlin3();
  public static final int access$getA$cp();
  public static final void access$setA$cp(int);
  static {};
}


(2) javap -c å°†å­—èŠ‚ç åç¼–è¯‘å‡ºæ¥
// è¯´æ˜: è¿™é‡Œæ²¡æœ‰å‡ºç°method()é™æ€æ–¹æ³•ï¼Œè¿™å°±éªŒè¯äº†è¿™å¥è¯ã€Œè™½ç„¶ä¼´ç”Ÿå¯¹è±¡çš„æˆå‘˜çœ‹èµ·æ¥åƒæ˜¯Javaä¸­çš„é™æ€æˆå‘˜ï¼Œ
ä½†åœ¨è¿è¡ŒæœŸï¼Œä»–ä»¬ä¾æ—§æ˜¯çœŸå®å¯¹è±¡(çœŸå®å¯¹è±¡æŒ‡çš„æ˜¯MyObject)çš„å®ä¾‹æˆå‘˜ã€ï¼Œ==> method()æ–¹æ³•å¹¶ä¸ä¼šæˆä¸ºHiKotlin3ç±»çš„é™æ€æˆå‘˜

public final class Kotlinå­¦ä¹ .kotlinåŸºç¡€.pkg7_ä¼´ç”Ÿå¯¹è±¡.HiKotlin3 {
  public static final Kotlinå­¦ä¹ .kotlinåŸºç¡€.pkg7_ä¼´ç”Ÿå¯¹è±¡.HiKotlin3$MyObject MyObject;

  // HiKotlin3çš„æ„é€ æ–¹æ³•
  public Kotlinå­¦ä¹ .kotlinåŸºç¡€.pkg7_ä¼´ç”Ÿå¯¹è±¡.HiKotlin3();
    Code:
       0: aload_0
       1: invokespecial #8                  // Method java/lang/Object."<init>":()V
       4: return

  public static final int access$getA$cp();
    Code:
       0: getstatic     #16                 // Field a:I
       3: ireturn

  public static final void access$setA$cp(int);
    Code:
       0: iload_0
       1: putstatic     #16                 // Field a:I
       4: return

  // é™æ€ä»£ç å—
  static {};
    Code:
       0: new           #22                 // class Kotlinå­¦ä¹ /kotlinåŸºç¡€.pkg7_ä¼´ç”Ÿå¯¹è±¡/HiKotlin3$MyObject
       3: dup
       4: aconst_null
       5: invokespecial #25                 // Method Kotlinå­¦ä¹ /kotlinåŸºç¡€.pkg7_ä¼´ç”Ÿå¯¹è±¡/HiKotlin3$MyObject."<init>":(Lkotlin/jvm/internal/DefaultConstructorMarker;)V
       8: putstatic     #29                 // Field MyObject:LKotlinå­¦ä¹ /kotlinåŸºç¡€.pkg7_ä¼´ç”Ÿå¯¹è±¡/HiKotlin3$MyObject;
      11: bipush        100
      13: putstatic     #16                 // Field a:I
      16: return
}


 */
